polyswarmtransaction/__init__.py
polyswarmtransaction/__main__.py
polyswarmtransaction/bounty.py
polyswarmtransaction/exceptions.py
polyswarmtransaction/nectar.py
polyswarmtransaction/transaction.py
polyswarm_transaction-0.4.1.dist-info/LICENSE
polyswarm_transaction-0.4.1.dist-info/METADATA
polyswarm_transaction-0.4.1.dist-info/WHEEL
polyswarm_transaction-0.4.1.dist-info/top_level.txt
polyswarm_transaction-0.4.1.dist-info/RECORD
