Metadata-Version: 2.1
Name: polyswarm-transaction
Version: 0.4.1
Summary: Library for building & signing transactions for the PolySwarm sidechain
Home-page: https://github.com/polyswarm/polyswarm-transaction
Author: PolySwarm Developers
Author-email: info@polyswarm.io
License: MIT
Platform: UNKNOWN
Classifier: Intended Audience :: Developers
Classifier: License :: OSI Approved :: MIT License
Classifier: Operating System :: OS Independent
Classifier: Programming Language :: Python :: 3.6
Classifier: Programming Language :: Python :: 3.7
Classifier: Programming Language :: Python :: Implementation :: PyPy
Requires-Python: >=3.6,<4
Requires-Dist: hexbytes (~=0.2.0)
Requires-Dist: jsonschema (~=3.2.0)
Requires-Dist: polyswarm-artifact (~=1.4.2)
Requires-Dist: web3 (~=5.6.0)
Requires-Dist: click (~=7.1.2)
Requires-Dist: dataclasses (==0.7) ; python_version == "3.6"
